DataMemory.sv
module DataMemory #(
    parameter   WIDTH = 32,
                DATA_WIDTH = 8
)(
    input   logic                   clk,
    input   logic                   WE,
    input   logic [WIDTH-1:0]       A,
    input   logic [WIDTH-1:0]       WD,
    output  logic [WIDTH-1:0]       RD
);

logic [DATA_WIDTH-1:0] DataMemory_array [32'h1ffff : 32'h0]; // according to memory map provided in brief

initial begin
     $display ("Loading DataMemory.");
     $readmemh("gaussian.mem", DataMemory_array, 32'h10000);
     $display ("DataMemory loaded");
 end;

always_comb
    RD = {DataMemory_array[A + 3], DataMemory_array[A + 2], DataMemory_array[A + 1], DataMemory_array[A]};

always_ff @ (posedge clk) begin
    if(WE == 1'b1) begin
        DataMemory_array[A] <= WD[7:0];
        DataMemory_array[A + 1] <= WD[15:8];
        DataMemory_array[A + 2] <= WD[23:16];
        DataMemory_array[A + 3] <= WD[31:24];
    end
end

endmodule

DataMemory.vcd
$version Generated by VerilatedVcd $end
$date Fri Dec  1 07:07:51 2023 $end
$timescale 1ps $end

 $scope module TOP $end
  $var wire 32 % A [31:0] $end
  $var wire 32 ' RD [31:0] $end
  $var wire 32 & WD [31:0] $end
  $var wire  1 $ WE $end
  $var wire  1 # clk $end
  $scope module DataMemory $end
   $var wire 32 % A [31:0] $end
   $var wire 32 ) DATA_WIDTH [31:0] $end
   $var wire 32 ' RD [31:0] $end
   $var wire 32 & WD [31:0] $end
   $var wire  1 $ WE $end
   $var wire 32 ( WIDTH [31:0] $end
   $var wire  1 # clk $end
  $upscope $end
 $upscope $end
$enddefinitions $end


#0
0#
0$
b00000000000000000000000000000000 %
b00000000000000000000000000000000 &
b00000000000000000000000000000000 '
b00000000000000000000000000100000 (
b00000000000000000000000000001000 )
#1
1#
#2
0#
b00000000000000010000000000000000 %
#3
1#
b11101110111011101110111011101111 '
#4
0#
b00000000000000010000000000000100 %
#5
1#
b11101101111011011110111011101110 '
#6
0#
b00000000000000010000000000001000 %
#7
1#
b11101010111010111110110011101100 '
#8
0#
b00000000000000010000000000001100 %
#9
1#
b11100110111001111110100011101001 '
#10
0#
b00000000000000010000000000010000 %
#11
1#
b11100010111000111110010011100101 '
#12
0#
b00000000000000010000000000010100 %
#13
1#
b11011100110111011101111111100000 '
#14
0#
b00000000000000010000000000011000 %
#15
1#
b11010101110101111101100111011010 '
#16
0#
b00000000000000010000000000011100 %
#17
1#
b11001101110011111101000111010011 '
#18
0#
b00000000000000010000000000100000 %
#19
1#
b11000101110001111100100111001011 '
#20
0#
b00000000000000010000000000100100 %
#21
1#
b10111100101111101100000011000011 '
#22
0#
b00000000000000010000000000101000 %
#23
1#
b10110010101101001011011110111001 '
#24
0#
b00000000000000010000000000101100 %
#25
1#
b10100111101010101010110110101111 '
#26
0#
b00000000000000010000000000110000 %
#27
1#
b10011100100111111010001010100101 '
#28
0#
b00000000000000010000000000110100 %
#29
1#
b10010001100101001001011110011001 '
#30
0#
b00000000000000010000000000111000 %
#31
1#
b10000101100010001000101110001110 '
#32
0#
b00000000000000010000000000111100 %
#33
1#
b01111010011111011000000010000010 '
#34
0#
b00000000000000010000000001000000 %
#35
1#
b01101110011100010111010001110111 '
#36
0#
b00000000000000010000000001000100 %
#37
1#
b01100010011001010110100001101011 '
#38
0#
b00000000000000010000000001001000 %
#39
1#
b01010111010110100101110101011111 '
