rom.sv
module rom  #(
        parameter   ADDRESS_WIDTH = 32,     // width of the input and output
                    DATA_WIDTH = 8          // byte addressing: 4 * 8 = 32 bits, hence why we have PC + 4
)(
    input logic  [ADDRESS_WIDTH-1:0]       addr,
    input logic                            clk,
    output logic [ADDRESS_WIDTH-1:0]       dout
);

logic [DATA_WIDTH-1:0] rom_array [32'hBFC00FFF:32'hBFC00000]; //range of ROM specified

initial begin
        $display("Loading rom.");
        $readmemh("instruction.mem", rom_array);
end;

always_ff @(posedge clk)     // need little endian byte addressing
    dout = {rom_array[addr + 3],        // bits 31:24
            rom_array[addr + 2],        // bits 23:16
            rom_array[addr + 1],        // bits 15:8
            rom_array[addr]};           // bits 7:0

endmodule

rom.vcd
$version Generated by VerilatedVcd $end
$date Fri Dec  1 12:11:09 2023 $end
$timescale 1ps $end

 $scope module TOP $end
  $var wire 32 # addr [31:0] $end
  $var wire  1 $ clk $end
  $var wire 32 % dout [31:0] $end
  $scope module rom $end
   $var wire 32 & ADDRESS_WIDTH [31:0] $end
   $var wire 32 ' DATA_WIDTH [31:0] $end
   $var wire 32 # addr [31:0] $end
   $var wire  1 $ clk $end
   $var wire 32 % dout [31:0] $end
  $upscope $end
 $upscope $end
$enddefinitions $end


#0
b00000000000000000000000000000000 #
0$
b00000000000000000000000000000000 %
b00000000000000000000000000100000 &
b00000000000000000000000000001000 '
#1
1$
#2
0$
#3
1$
b00001111111100000000001100010011 %
#4
b00000000000000000000000000000001 #
0$
#5
1$
b00010011000011111111000000000011 %
#6
b00000000000000000000000000000010 #
0$
#7
1$
b00000101000100110000111111110000 %
#8
b00000000000000000000000000000011 #
0$
#9
1$
b00000000000001010001001100001111 %
#10
b00000000000000000000000000000100 #
0$
#11
1$
b00000000000000000000010100010011 %
#12
b00000000000000000000000000000101 #
0$
#13
1$
b10010011000000000000000000000101 %
#14
b00000000000000000000000000000110 #
0$
#15
1$
b00000101100100110000000000000000 %
#16
b00000000000000000000000000000111 #
0$
#17
1$
b00000000000001011001001100000000 %
#18
b00000000000000000000000000001000 #
0$
#19
1$
b00000000000000000000010110010011 %
#20
b00000000000000000000000000001001 #
0$
#21
1$
b00010011000000000000000000000101 %
#22
b00000000000000000000000000001010 #
0$
#23
1$
b10000101000100110000000000000000 %
#24
b00000000000000000000000000001011 #
0$
#25
1$
b00000101100001010001001100000000 %
#26
b00000000000000000000000000001100 #
0$
#27
1$
b00000000000001011000010100010011 %
#28
b00000000000000000000000000001101 #
0$
#29
1$
b10010011000000000000010110000101 %
#30
b00000000000000000000000000001110 #
0$
#31
1$
b10000101100100110000000000000101 %
#32
b00000000000000000000000000001111 #
0$
#33
1$
b00010101100001011001001100000000 %
#34
b00000000000000000000000000010000 #
0$
#35
1$
b00000000000101011000010110010011 %
#36
b00000000000000000000000000010001 #
0$
#37
1$
b11100011000000000001010110000101 %
#38
b00000000000000000000000000010010 #
0$
#39
1$
b10011100111000110000000000010101 %
