SignExtend.sv
module SignExtend#(
        parameter DATA_WIDTH = 32
)(
    input logic [DATA_WIDTH-1:0]    Imm_i,
    input logic [2:0]               ImmSrc,
    output logic [DATA_WIDTH-1:0]   Imm_o
);

always_comb begin
    case(ImmSrc)
    //I-type
    3'b000: Imm_o = {{21{Imm_i[31]}}, Imm_i[30:20]};
    //U-type
    3'b001: Imm_o = {Imm_i[31:12], 12'b0};
    //S-type
    3'b010: Imm_o = {{21{Imm_i[31]}}, Imm_i[30:25], Imm_i[11:7]};
    //B-type
    3'b011: Imm_o = {{20{Imm_i[31]}}, Imm_i[7], Imm_i[30:25], Imm_i[11:8], 1'b0};
    //J-type
    3'b100: Imm_o = {{12{Imm_i[31]}}, Imm_i[19:12], Imm_i[20], Imm_i[30:21], 1'b0};
    endcase
end

endmodule

rom.sv
module rom  #(
        parameter   WIDTH = 32,     // width of the input and output
                    DATA_WIDTH = 8  // byte addressing: 4 * 8 = 32 bits, hence why we have PC + 4
)(
    input logic  [WIDTH-1:0]       addr,
    input logic                    clk,
    output logic [WIDTH-1:0]       dout
);

logic [DATA_WIDTH-1:0] rom_array [2**5:0];

initial begin
        $display("Loading rom.");
        $readmemh("instruction.mem", rom_array);
        $display("rom Loaded");
end;

always_ff@(posedge clk)
    dout = {rom_array[addr + 3],    // bits 31:24
            rom_array[addr + 2],    // bits 23:16
            rom_array[addr + 1],    // bits 15:8
            rom_array[addr]};       // bits 7:0

endmodule

test.sv
module test#(
    parameter DATA_WIDTH = 32
)(
    input logic clk,
    input logic [DATA_WIDTH-1:0]    addr,
    input logic [2:0]               ImmSrc,
    output logic [DATA_WIDTH-1:0]   Imm_o
);

logic [DATA_WIDTH-1:0] instr_wire;

rom input_s(
    .clk(clk),
    .addr(addr),
    .dout(instr_wire)
);

SignExtend extend(
    .Imm_i(instr_wire),
    .ImmSrc(ImmSrc),
    .Imm_o(Imm_o)
);

endmodule

test.vcd
$version Generated by VerilatedVcd $end
$date Thu Nov 30 13:49:43 2023 $end
$timescale 1ps $end

 $scope module TOP $end
  $var wire  3 % ImmSrc [2:0] $end
  $var wire 32 & Imm_o [31:0] $end
  $var wire 32 $ addr [31:0] $end
  $var wire  1 # clk $end
  $scope module test $end
   $var wire 32 ( DATA_WIDTH [31:0] $end
   $var wire  3 % ImmSrc [2:0] $end
   $var wire 32 & Imm_o [31:0] $end
   $var wire 32 $ addr [31:0] $end
   $var wire  1 # clk $end
   $var wire 32 ' instr_wire [31:0] $end
   $scope module extend $end
    $var wire 32 ( DATA_WIDTH [31:0] $end
    $var wire  3 % ImmSrc [2:0] $end
    $var wire 32 ' Imm_i [31:0] $end
    $var wire 32 & Imm_o [31:0] $end
   $upscope $end
   $scope module input_s $end
    $var wire 32 ) DATA_WIDTH [31:0] $end
    $var wire 32 ( WIDTH [31:0] $end
    $var wire 32 $ addr [31:0] $end
    $var wire  1 # clk $end
    $var wire 32 ' dout [31:0] $end
   $upscope $end
  $upscope $end
 $upscope $end
$enddefinitions $end


#0
0#
b00000000000000000000000000000000 $
b011 %
b00000000000000000000000000000000 &
b00000000000000000000000000000000 '
b00000000000000000000000000100000 (
b00000000000000000000000000001000 )
#1
1#
#2
0#
#3
1#
b11111111111111111111000000000000 &
b10000000000000000000000000000000 '
#4
0#
b00000000000000000000000000000001 $
#5
1#
b11111111111111111111011111100000 &
b11111111100000000000000000000000 '
#6
0#
b00000000000000000000000000000010 $
#7
1#
b11111111111111111000000000000000 '
#8
0#
b00000000000000000000000000000011 $
#9
1#
b00000000000000000000100000011110 &
b00000000111111111111111110000000 '
#10
0#
b00000000000000000000000000000100 $
#11
1#
b00000000000000000000100100011110 &
b00010000000000001111111111111111 '
#12
0#
b00000000000000000000000000000101 $
#13
1#
b11111111111111111111101110000000 &
b10111001000100000000000011111111 '
#14
0#
b00000000000000000000000000000110 $
#15
1#
b11111111111111111111011000000000 &
b11100000101110010001000000000000 '
#16
0#
b00000000000000000000000000000111 $
#17
1#
b11111111111111111111001111110010 &
b10111111111000001011100100010000 '
#18
0#
b00000000000000000000000000001000 $
#19
1#
b00000000000000000000100000000000 &
b00000000101111111110000010111001 '
#20
0#
b00000000000000000000000000001001 $
#21
1#
b00000000000000000000100000011110 &
b00000000000000001011111111100000 '
#22
0#
b00000000000000000000000000001010 $
#23
1#
b00000000000000000000100000000000 &
b00000000000000000000000010111111 '
#24
0#
b00000000000000000000000000001011 $
#25
1#
b00000000000000000000000000000000 &
b00000000000000000000000000000000 '
#26
0#
b00000000000000000000000000001100 $
#27
1#
#28
0#
b00000000000000000000000000001101 $
#29
1#
#30
0#
b00000000000000000000000000001110 $
#31
1#
#32
0#
b00000000000000000000000000001111 $
#33
1#
#34
0#
b00000000000000000000000000010000 $
#35
1#
#36
0#
b00000000000000000000000000010001 $
#37
1#
#38
0#
b00000000000000000000000000010010 $
