two_way_set_associative_cache.sv
module two_way_set_associative_cache #(
    parameter DATA_WIDTH = 32,
                TAG_WIDTH = 27,
                SET_WIDTH = 3,
                OFFSET_WIDTH = 2,
                CACHE_LENGTH = 8
) (
    input logic clk,
    input logic write_enable,
    input logic [DATA_WIDTH-1:0] address,
    input logic [DATA_WIDTH-1:0] data,
    output logic cache_hit,
    output logic [DATA_WIDTH-1:0] cache_data,
    output logic [DATA_WIDTH-1:0] write_back_data,
    output logic [DATA_WIDTH-1:0] write_back_address
);
// LRU counter
logic lru_counter_0 [CACHE_LENGTH-1:0];
logic lru_counter_1 [CACHE_LENGTH-1:0];

//cache array
logic V_0 [CACHE_LENGTH-1:0];
logic D_0 [CACHE_LENGTH-1:0]; //dirty bit
logic [TAG_WIDTH-1:0] tag_0 [CACHE_LENGTH-1:0];
logic [DATA_WIDTH-1:0] data_0 [CACHE_LENGTH-1:0];

logic V_1 [CACHE_LENGTH-1:0];
logic D_1 [CACHE_LENGTH-1:0];
logic [TAG_WIDTH-1:0] tag_1 [CACHE_LENGTH-1:0];
logic [DATA_WIDTH-1:0] data_1 [CACHE_LENGTH-1:0];

//tag and set
logic [SET_WIDTH-1:0] data_set;
logic [TAG_WIDTH-1:0] data_tag;

assign data_set = address[4:2];
assign data_tag = address[32:5];

//cache hit
logic cache_hit_0, cache_hit_1; //cache hit way 0 and 1
assign cache_hit_0 = ((tag_0[data_set] == data_tag) && V_0[data_set]);
assign cache_hit_1 = ((tag_1[data_set] == data_tag) && V_1[data_set]);
assign cache_hit = cache_hit_0 || cache_hit_1;

always_comb begin
    if(cache_hit) begin
        //write operation
        if(write_enable) begin
            if(cache_hit_1) begin
                data_1[data_set] <= data;
                D_1[data_set] <= 1'b1;
                lru_counter_1[data_set] <= lru_counter_1[data_set] + 1;
            end
            else begin
                data_0[data_set] <= data;
                D_0[data_set] <= 1'b1;
                lru_counter_0[data_set] <= lru_counter_0[data_set] + 1;
            end
        end
        //read operation
        else begin
            if(cache_hit_1) begin
                cache_data = data_1[data_set];
                lru_counter_1[data_set] <= lru_counter_1[data_set] + 1;
            end
            else begin
                cache_data = data_0[data_set];
                lru_counter_0[data_set] <= lru_counter_0[data_set] + 1;
            end
        end
    end
end

//cache miss
always_ff @(negedge clk) begin
    if(!cache_hit) begin
        //compulsory miss
        if(!V_0[data_set]) begin
            tag_0[data_set] <= data_tag;
            data_0[data_set] <= data;
            V_0[data_set] <= 1'b1;
            D_0[data_set] <= 1'b0;
            lru_counter_0[data_set] <= 0;
        end
        else if (!V_1[data_set]) begin
            tag_1[data_set] <= data_tag;
            data_1[data_set] <= data;
            V_1[data_set] <= 1'b1;
            D_1[data_set] <= 1'b0;
            lru_counter_1[data_set] <= 0;
        end
        //capacity miss -> LRU eviction policy
        else if (V_1[data_set] && V_0[data_set]) begin
            if (lru_counter_0[data_set] < lru_counter_1[data_set]) begin
                if(D_0[data_set]) begin //write back to main mem
                    write_back_data = data_0[data_set];
                    write_back_address = {tag_0[data_set], data_set, {OFFSET_WIDTH{1'b0}}};
                    D_0[data_set] <= 1'b0;
                end
                //evict and fill
                tag_0[data_set] <= data_tag;
                data_0[data_set] <= data;
                lru_counter_0[data_set] <= 0;
            end
            else begin
                if(D_1[data_set]) begin
                    write_back_data = data_1[data_set]; 
                    write_back_address = {tag_1[data_set], data_set, {OFFSET_WIDTH{1'b0}}};
                    D_1[data_set] <= 1'b0;
                end
                tag_1[data_set] <= data_tag;
                data_1[data_set] <= data;
                lru_counter_1[data_set] <= 0;
            end
        end
    end
end
endmodule

two_way_set_associative_cache.vcd
$version Generated by VerilatedVcd $end
$date Thu Dec 14 10:58:17 2023 $end
$timescale 1ps $end

 $scope module TOP $end
  $var wire 32 u address [31:0] $end
  $var wire 32 x cache_data [31:0] $end
  $var wire  1 w cache_hit $end
  $var wire  1 s clk $end
  $var wire 32 v data [31:0] $end
  $var wire 32 z write_back_address [31:0] $end
  $var wire 32 y write_back_data [31:0] $end
  $var wire  1 t write_enable $end
  $scope module two_way_set_associative_cache $end
   $var wire 32 %! CACHE_LENGTH [31:0] $end
   $var wire 32 !! DATA_WIDTH [31:0] $end
   $var wire  1 S D_0[0] $end
   $var wire  1 T D_0[1] $end
   $var wire  1 U D_0[2] $end
   $var wire  1 V D_0[3] $end
   $var wire  1 W D_0[4] $end
   $var wire  1 X D_0[5] $end
   $var wire  1 Y D_0[6] $end
   $var wire  1 Z D_0[7] $end
   $var wire  1 c D_1[0] $end
   $var wire  1 d D_1[1] $end
   $var wire  1 e D_1[2] $end
   $var wire  1 f D_1[3] $end
   $var wire  1 g D_1[4] $end
   $var wire  1 h D_1[5] $end
   $var wire  1 i D_1[6] $end
   $var wire  1 j D_1[7] $end
   $var wire 32 $! OFFSET_WIDTH [31:0] $end
   $var wire 32 #! SET_WIDTH [31:0] $end
   $var wire 32 "! TAG_WIDTH [31:0] $end
   $var wire  1 # V_0[0] $end
   $var wire  1 $ V_0[1] $end
   $var wire  1 % V_0[2] $end
   $var wire  1 & V_0[3] $end
   $var wire  1 ' V_0[4] $end
   $var wire  1 ( V_0[5] $end
   $var wire  1 ) V_0[6] $end
   $var wire  1 * V_0[7] $end
   $var wire  1 3 V_1[0] $end
   $var wire  1 4 V_1[1] $end
   $var wire  1 5 V_1[2] $end
   $var wire  1 6 V_1[3] $end
   $var wire  1 7 V_1[4] $end
   $var wire  1 8 V_1[5] $end
   $var wire  1 9 V_1[6] $end
   $var wire  1 : V_1[7] $end
   $var wire 32 u address [31:0] $end
   $var wire 32 x cache_data [31:0] $end
   $var wire  1 w cache_hit $end
   $var wire  1 } cache_hit_0 $end
   $var wire  1 ~ cache_hit_1 $end
   $var wire  1 s clk $end
   $var wire 32 v data [31:0] $end
   $var wire 32 [ data_0[0] [31:0] $end
   $var wire 32 \ data_0[1] [31:0] $end
   $var wire 32 ] data_0[2] [31:0] $end
   $var wire 32 ^ data_0[3] [31:0] $end
   $var wire 32 _ data_0[4] [31:0] $end
   $var wire 32 ` data_0[5] [31:0] $end
   $var wire 32 a data_0[6] [31:0] $end
   $var wire 32 b data_0[7] [31:0] $end
   $var wire 32 k data_1[0] [31:0] $end
   $var wire 32 l data_1[1] [31:0] $end
   $var wire 32 m data_1[2] [31:0] $end
   $var wire 32 n data_1[3] [31:0] $end
   $var wire 32 o data_1[4] [31:0] $end
   $var wire 32 p data_1[5] [31:0] $end
   $var wire 32 q data_1[6] [31:0] $end
   $var wire 32 r data_1[7] [31:0] $end
   $var wire  3 { data_set [2:0] $end
   $var wire 27 | data_tag [26:0] $end
   $var wire  1 C lru_counter_0[0] $end
   $var wire  1 D lru_counter_0[1] $end
   $var wire  1 E lru_counter_0[2] $end
   $var wire  1 F lru_counter_0[3] $end
   $var wire  1 G lru_counter_0[4] $end
   $var wire  1 H lru_counter_0[5] $end
   $var wire  1 I lru_counter_0[6] $end
   $var wire  1 J lru_counter_0[7] $end
   $var wire  1 K lru_counter_1[0] $end
   $var wire  1 L lru_counter_1[1] $end
   $var wire  1 M lru_counter_1[2] $end
   $var wire  1 N lru_counter_1[3] $end
   $var wire  1 O lru_counter_1[4] $end
   $var wire  1 P lru_counter_1[5] $end
   $var wire  1 Q lru_counter_1[6] $end
   $var wire  1 R lru_counter_1[7] $end
   $var wire 27 + tag_0[0] [26:0] $end
   $var wire 27 , tag_0[1] [26:0] $end
   $var wire 27 - tag_0[2] [26:0] $end
   $var wire 27 . tag_0[3] [26:0] $end
   $var wire 27 / tag_0[4] [26:0] $end
   $var wire 27 0 tag_0[5] [26:0] $end
   $var wire 27 1 tag_0[6] [26:0] $end
   $var wire 27 2 tag_0[7] [26:0] $end
   $var wire 27 ; tag_1[0] [26:0] $end
   $var wire 27 < tag_1[1] [26:0] $end
   $var wire 27 = tag_1[2] [26:0] $end
   $var wire 27 > tag_1[3] [26:0] $end
   $var wire 27 ? tag_1[4] [26:0] $end
   $var wire 27 @ tag_1[5] [26:0] $end
   $var wire 27 A tag_1[6] [26:0] $end
   $var wire 27 B tag_1[7] [26:0] $end
   $var wire 32 z write_back_address [31:0] $end
   $var wire 32 y write_back_data [31:0] $end
   $var wire  1 t write_enable $end
  $upscope $end
 $upscope $end
$enddefinitions $end


#0
0#
0$
0%
0&
0'
0(
0)
0*
b000000000000000000000000000 +
b000000000000000000000000000 ,
b000000000000000000000000000 -
b000000000000000000000000000 .
b000000000000000000000000000 /
b000000000000000000000000000 0
b000000000000000000000000000 1
b000000000000000000000000000 2
03
04
05
06
07
08
09
0:
b000000000000000000000000000 ;
b000000000000000000000000000 <
b000000000000000000000000000 =
b000000000000000000000000000 >
b000000000000000000000000000 ?
b000000000000000000000000000 @
b000000000000000000000000000 A
b000000000000000000000000000 B
0C
0D
0E
0F
0G
0H
0I
0J
0K
0L
0M
0N
0O
0P
0Q
0R
0S
0T
0U
0V
0W
0X
0Y
0Z
b00000000000000000000000000000000 [
b00000000000000000000000000000000 \
b00000000000000000000000000000000 ]
b00000000000000000000000000000000 ^
b00000000000000000000000000000000 _
b00000000000000000000000000000000 `
b00000000000000000000000000000000 a
b00000000000000000000000000000000 b
0c
0d
0e
0f
0g
0h
0i
0j
b00000000000000000000000000000000 k
b00000000000000000000000000000000 l
b00000000000000000000000000000000 m
b00000000000000000000000000000000 n
b00000000000000000000000000000000 o
b00000000000000000000000000000000 p
b00000000000000000000000000000000 q
b00000000000000000000000000000000 r
0s
1t
b00000000000000000000000000000000 u
b00000000000000000000000000000000 v
0w
b00000000000000000000000000000000 x
b00000000000000000000000000000000 y
b00000000000000000000000000000000 z
b000 {
b000000000000000000000000000 |
0}
0~
b00000000000000000000000000100000 !!
b00000000000000000000000000011011 "!
b00000000000000000000000000000011 #!
b00000000000000000000000000000010 $!
b00000000000000000000000000001000 %!
#1
1s
#2
1#
0s
1w
1}
#3
1C
1S
1s
#4
0s
b00000000000000000000000000010111 u
b00000000000000000000000000010111 v
b101 {
0}
#5
1H
1X
b00000000000000000000000000010111 `
1s
0w
#6
1(
0H
0X
0s
b00000000000000000000000000101110 u
b00000000000000000000000000101110 v
1w
b011 {
b000000000000000000000000001 |
#7
1F
1V
b00000000000000000000000000101110 ^
1s
0w
#8
1&
b000000000000000000000000001 .
0F
0V
0s
b00000000000000000000000001000101 u
b00000000000000000000000001000101 v
1w
b001 {
b000000000000000000000000010 |
#9
1D
1T
b00000000000000000000000001000101 \
1s
0w
#10
1$
b000000000000000000000000010 ,
0D
0T
0s
b00000000000000000000000001011100 u
b00000000000000000000000001011100 v
1w
b111 {
#11
1J
1Z
b00000000000000000000000001011100 b
1s
0w
#12
1*
b000000000000000000000000010 2
0J
0Z
0s
0t
b00000000000000000000000000010111 u
b00000000000000000000000000010111 v
1w
b101 {
b000000000000000000000000000 |
1}
#13
1H
1s
b00000000000000000000000000010111 x
#14
0s
b00000000000000000000000000101110 u
b00000000000000000000000000101110 v
b011 {
b000000000000000000000000001 |
#15
1F
1s
b00000000000000000000000000101110 x
#16
0s
b00000000000000000000000001000101 u
b00000000000000000000000001000101 v
b001 {
b000000000000000000000000010 |
#17
1D
1s
b00000000000000000000000001000101 x
